fourinsight/api/__init__.py
fourinsight/api/_constants.json
fourinsight/api/appdirs.py
fourinsight/api/authenticate.py
fourinsight_api-0.1.21.dist-info/METADATA
fourinsight_api-0.1.21.dist-info/WHEEL
fourinsight_api-0.1.21.dist-info/top_level.txt
fourinsight_api-0.1.21.dist-info/RECORD
