Metadata-Version: 2.4
Name: fourinsight-api
Version: 0.1.21
Summary: 4Insight Python API
Home-page: https://4insight.io
Author: 4Subsea
Author-email: support@4subsea.com
Project-URL: Documentation, https://docs.4insight.io/api/python/latest/
Classifier: License :: OSI Approved :: MIT License
Classifier: Operating System :: OS Independent
Classifier: Programming Language :: Python :: 3.11
Classifier: Programming Language :: Python :: 3.12
Classifier: Programming Language :: Python :: 3.13
Requires-Python: >=3.11
Requires-Dist: oauthlib
Requires-Dist: requests-oauthlib
Requires-Dist: importlib_resources
Requires-Dist: sphinxcontrib-video
